bvx_es/__init__.py
bvx_es/decorator.py
bvx_es/elasticsearch.py
bvx_es-0.0.8.dist-info/LICENSE
bvx_es-0.0.8.dist-info/METADATA
bvx_es-0.0.8.dist-info/WHEEL
bvx_es-0.0.8.dist-info/top_level.txt
bvx_es-0.0.8.dist-info/RECORD
